snippycode/__init__.py
snippycode/__main__.py
snippycode/snippyClipboard.py
snippycode/snippyObjects.py
snippycode/snippySnippets.py
snippycode/snippycode.py
snippycode-0.1.5.dist-info/LICENSE.md
snippycode-0.1.5.dist-info/METADATA
snippycode-0.1.5.dist-info/WHEEL
snippycode-0.1.5.dist-info/entry_points.txt
snippycode-0.1.5.dist-info/top_level.txt
snippycode-0.1.5.dist-info/RECORD
